agl_model_zoo/__init__.py
agl_model_zoo/dataloaders/__init__.py
agl_model_zoo/dataloaders/cifar10_dataloader.py
agl_model_zoo/dataloaders/image_dataloader.py
agl_model_zoo/models/__init__.py
agl_model_zoo/models/multilabel_image_classifier.py
agl_model_zoo/training/__init__.py
agl_model_zoo/training/legacy_multilabel_trainer.py
agl_model_zoo/utils/__init__.py
agl_model_zoo-0.1.5.dist-info/LICENSE
agl_model_zoo-0.1.5.dist-info/METADATA
agl_model_zoo-0.1.5.dist-info/WHEEL
agl_model_zoo-0.1.5.dist-info/RECORD
