Metadata-Version: 2.1
Name: agl-model-zoo
Version: 0.1.5
Summary: 
License: MIT
Author: Thomas J. Lux
Requires-Python: >=3.11,<3.12
Classifier: License :: OSI Approved :: MIT License
Classifier: Programming Language :: Python :: 3
Classifier: Programming Language :: Python :: 3.11
Requires-Dist: albumentations (>=1.3.1,<2.0.0)
Requires-Dist: icecream (>=2.1.3,<3.0.0)
Requires-Dist: opencv-python (>=4.8.1.78,<5.0.0.0)
Requires-Dist: pandas (>=2.1.2,<3.0.0)
